[
    {
        "model": "API.inventaris",
        "pk": 1,
        "fields": {
            "nama": "Laptop Asus",
            "kode_inventaris": "AS-11223",
            "kondisi": "baik",
            "keterangan": "Asus TUF Rtx 2050 ",
            "jumlah": 10,
            "id_jenis": 1,
            "id_ruang": 1,
            "id_petugas": 1,
            "tanggal_register": "2023-10-01"
        }
    },
    {
        "model": "API.inventaris",
        "pk": 2,
        "fields": {
            "nama": "Proyektor Epson",
            "kode_inventaris": "EPS-1233",
            "kondisi": "baik",
            "keterangan": "Proyektor Epson",
            "jumlah": 5,
            "id_jenis": 2,
            "id_ruang": 2,
            "id_petugas": 2,
            "tanggal_register": "2023-10-02"
        }
    },
    {
        "model": "API.inventaris",
        "pk": 3,
        "fields": {
            "nama": "Printer HP",
            "kode_inventaris": "HP-1123",
            "kondisi": "baik",
            "keterangan": "Printer HP rusak, perlu perbaikan",
            "jumlah": 5,
            "id_jenis": 1,
            "id_ruang": 1,
            "id_petugas": 1,
            "tanggal_register": "2023-10-03"
        }
    },
    {
        "model": "API.inventaris",
        "pk": 4,
        "fields": {
            "nama": "Scanner Canon",
            "kode_inventaris": "CN-2132",
            "kondisi": "baik",
            "keterangan": "Scanner Canon untuk dokumen",
            "jumlah": 5,
            "id_jenis": 2,
            "id_ruang": 2,
            "id_petugas": 2,
            "tanggal_register": "2023-10-04"
        }
    },
    {
        "model": "API.inventaris",
        "pk": 5,
        "fields": {
            "nama": "Meja Kayu Jati",
            "kode_inventaris": "JT-3122",
            "kondisi": "baik",
            "keterangan": "Meja Kayu Jati untuk kerja",
            "jumlah": 5,
            "id_jenis": 1,
            "id_ruang": 1,
            "id_petugas": 1,
            "tanggal_register": "2023-10-05"
        }
    },
    {
        "model": "API.inventaris",
        "pk": 6,
        "fields": {
            "nama": "Kursi Ergonomis Ergotec",
            "kode_inventaris": "ERG-2314",
            "kondisi": "baik",
            "keterangan": "Kursi kantor ergonomis Ergotec",
            "jumlah": 5,
            "id_jenis": 2,
            "id_ruang": 2,
            "id_petugas": 2,
            "tanggal_register": "2023-10-06"
        }
    },
    {
        "model": "API.inventaris",
        "pk": 7,
        "fields": {
            "nama": "Whiteboard NAGA",
            "kode_inventaris": "NG-00798",
            "kondisi": "baik",
            "keterangan": "Whiteboard NAGA untuk rapat",
            "jumlah": 5,
            "id_jenis": 1,
            "id_ruang": 1,
            "id_petugas": 1,
            "tanggal_register": "2023-10-07"
        }
    },
    {
        "model": "API.inventaris",
        "pk": 8,
        "fields": {
            "nama": "Televisi Samsung",
            "kode_inventaris": "SMSG-312",
            "kondisi": "baik",
            "keterangan": "Televisi Samsung 4k",
            "jumlah": 5,
            "id_jenis": 2,
            "id_ruang": 2,
            "id_petugas": 2,
            "tanggal_register": "2023-10-08"
        }
    },
    {
        "model": "API.inventaris",
        "pk": 9,
        "fields": {
            "nama": "AC Daikin",
            "kode_inventaris": "DKN-1231",
            "kondisi": "baik",
            "keterangan": "AC Daikin 2020",
            "jumlah": 5,
            "id_jenis": 1,
            "id_ruang": 1,
            "id_petugas": 1,
            "tanggal_register": "2023-10-09"
        }
    },
    {
        "model": "API.inventaris",
        "pk": 10,
        "fields": {
            "nama": "SNY-213",
            "kode_inventaris": "21098765",
            "kondisi": "baik",
            "keterangan": "Kamera Sony untuk dokumentasi",
            "jumlah": 3,
            "id_jenis": 2,
            "id_ruang": 2,
            "id_petugas": 2,
            "tanggal_register": "2023-10-10"
        }
    },
    {
        "model": "API.inventaris",
        "pk": 11,
        "fields": {
            "nama": "Laptop Asus",
            "kode_inventaris": "AS-11223",
            "kondisi": "rusak",
            "keterangan": "Asus TUF Rtx 2050 ",
            "jumlah": 1,
            "id_jenis": 1,
            "id_ruang": 1,
            "id_petugas": 1,
            "tanggal_register": "2023-10-01"
        }
    },
    {
        "model": "API.inventaris",
        "pk": 12,
        "fields": {
            "nama": "Scanner Canon",
            "kode_inventaris": "CN-2132",
            "kondisi": "rusak",
            "keterangan": "Scanner Canon untuk dokumen",
            "jumlah": 3,
            "id_jenis": 2,
            "id_ruang": 2,
            "id_petugas": 2,
            "tanggal_register": "2023-10-04"
        }
    },
    {
        "model": "API.inventaris",
        "pk": 2,
        "fields": {
            "nama": "Proyektor Epson",
            "kode_inventaris": "EPS-1233",
            "kondisi": "hilang",
            "keterangan": "Proyektor Epson",
            "jumlah": 2,
            "id_jenis": 2,
            "id_ruang": 2,
            "id_petugas": 2,
            "tanggal_register": "2023-10-02"
        }
    }
]
